README.md
setup.py
colibris_sendgrid.egg-info/PKG-INFO
colibris_sendgrid.egg-info/SOURCES.txt
colibris_sendgrid.egg-info/dependency_links.txt
colibris_sendgrid.egg-info/requires.txt
colibris_sendgrid.egg-info/top_level.txt
colibrissendgrid/__init__.py