Metadata-Version: 1.0
Name: colibris-sendgrid
Version: 1.0.0
Summary: SendGrid email backend for Colibris
Home-page: http://gitlab.com/safefleet/colibris-sendgrid
Author: UNKNOWN
Author-email: UNKNOWN
License: BSD
Platform: UNKNOWN
